{
  "fetchedAt": "2026-07-10T19:08:32Z",
  "series": "KXHIGHNY",
  "markets": [
    {
      "can_close_early": true,
      "close_time": "2026-07-12T04:59:00Z",
      "created_time": "2026-07-10T09:30:32.382416Z",
      "early_close_condition": "The Last Trading Time will be 11:59 PM ET on July 11, 2026 regardless of any data releases or events occurring. Expiration will occur on the sooner of the first 7:00 or 8:00\nAM ET following the release of the data for July 11, 2026, or one week after July 11, 2026.",
      "event_ticker": "KXHIGHNY-26JUL11",
      "expected_expiration_time": "2026-07-12T14:00:00Z",
      "expiration_time": "2026-07-18T14:00:00Z",
      "expiration_value": "",
      "floor_strike": 88,
      "last_price_dollars": "0.0100",
      "latest_expiration_time": "2026-07-18T14:00:00Z",
      "liquidity_dollars": "0.0000",
      "market_type": "binary",
      "no_ask_dollars": "1.0000",
      "no_bid_dollars": "0.9900",
      "no_sub_title": "89\u00b0 or above",
      "notional_value_dollars": "1.0000",
      "occurrence_datetime": "2026-07-11T14:00:00Z",
      "open_interest_fp": "1890.00",
      "open_time": "2026-07-10T14:00:00Z",
      "previous_price_dollars": "0.0000",
      "previous_yes_ask_dollars": "0.0000",
      "previous_yes_bid_dollars": "0.0000",
      "price_level_structure": "linear_cent",
      "price_ranges": [
        {
          "end": "1.0000",
          "start": "0.0000",
          "step": "0.0100"
        }
      ],
      "result": "",
      "rules_primary": "If the highest temperature recorded in Central Park, New York for July 11, 2026 as reported by the National Weather Service's Climatological Report (Daily), is greater than 88\u00b0, then the market resolves to Yes.",
      "rules_secondary": "Not all weather data is the same. While checking a source like AccuWeather or Google Weather may help guide your decision, the official and final value used to determine this market is the highest temperature as reported by the corresponding NWS Climatological Report (Daily) linked in the rules above. Preliminary NWS reporting and measurement methods may be subject to underlying rounding and conversion nuances. Traders should exercise caution when interpreting preliminary NWS data.",
      "settlement_timer_seconds": 3600,
      "status": "active",
      "strike_type": "greater",
      "subtitle": "89\u00b0 or above",
      "ticker": "KXHIGHNY-26JUL11-T88",
      "title": "Will the **high temp in NYC** be >88\u00b0 on Jul 11, 2026?",
      "updated_time": "2026-07-10T14:00:00.73332Z",
      "volume_24h_fp": "1911.00",
      "volume_fp": "1911.00",
      "yes_ask_dollars": "0.0100",
      "yes_ask_size_fp": "8776.00",
      "yes_bid_dollars": "0.0000",
      "yes_bid_size_fp": "0.00",
      "yes_sub_title": "89\u00b0 or above"
    },
    {
      "can_close_early": true,
      "cap_strike": 81,
      "close_time": "2026-07-12T04:59:00Z",
      "created_time": "2026-07-10T09:30:32.382416Z",
      "early_close_condition": "The Last Trading Time will be 11:59 PM ET on July 11, 2026 regardless of any data releases or events occurring. Expiration will occur on the sooner of the first 7:00 or 8:00\nAM ET following the release of the data for July 11, 2026, or one week after July 11, 2026.",
      "event_ticker": "KXHIGHNY-26JUL11",
      "expected_expiration_time": "2026-07-12T14:00:00Z",
      "expiration_time": "2026-07-18T14:00:00Z",
      "expiration_value": "",
      "last_price_dollars": "0.6300",
      "latest_expiration_time": "2026-07-18T14:00:00Z",
      "liquidity_dollars": "0.0000",
      "market_type": "binary",
      "no_ask_dollars": "0.3700",
      "no_bid_dollars": "0.3600",
      "no_sub_title": "80\u00b0 or below",
      "notional_value_dollars": "1.0000",
      "occurrence_datetime": "2026-07-11T14:00:00Z",
      "open_interest_fp": "1705.98",
      "open_time": "2026-07-10T14:00:00Z",
      "previous_price_dollars": "0.0000",
      "previous_yes_ask_dollars": "0.0000",
      "previous_yes_bid_dollars": "0.0000",
      "price_level_structure": "linear_cent",
      "price_ranges": [
        {
          "end": "1.0000",
          "start": "0.0000",
          "step": "0.0100"
        }
      ],
      "result": "",
      "rules_primary": "If the highest temperature recorded in Central Park, New York for July 11, 2026 as reported by the National Weather Service's Climatological Report (Daily), is less than 81\u00b0, then the market resolves to Yes.",
      "rules_secondary": "Not all weather data is the same. While checking a source like AccuWeather or Google Weather may help guide your decision, the official and final value used to determine this market is the highest temperature as reported by the corresponding NWS Climatological Report (Daily) linked in the rules above. Preliminary NWS reporting and measurement methods may be subject to underlying rounding and conversion nuances. Traders should exercise caution when interpreting preliminary NWS data.",
      "settlement_timer_seconds": 3600,
      "status": "active",
      "strike_type": "less",
      "subtitle": "80\u00b0 or below",
      "ticker": "KXHIGHNY-26JUL11-T81",
      "title": "Will the **high temp in NYC** be <81\u00b0 on Jul 11, 2026?",
      "updated_time": "2026-07-10T14:00:00.73332Z",
      "volume_24h_fp": "2079.12",
      "volume_fp": "2079.12",
      "yes_ask_dollars": "0.6400",
      "yes_ask_size_fp": "1.00",
      "yes_bid_dollars": "0.6300",
      "yes_bid_size_fp": "16.00",
      "yes_sub_title": "80\u00b0 or below"
    },
    {
      "can_close_early": true,
      "cap_strike": 88,
      "close_time": "2026-07-12T04:59:00Z",
      "created_time": "2026-07-10T09:30:32.382416Z",
      "early_close_condition": "The Last Trading Time will be 11:59 PM ET on July 11, 2026 regardless of any data releases or events occurring. Expiration will occur on the sooner of the first 7:00 or 8:00\nAM ET following the release of the data for July 11, 2026, or one week after July 11, 2026.",
      "event_ticker": "KXHIGHNY-26JUL11",
      "expected_expiration_time": "2026-07-12T14:00:00Z",
      "expiration_time": "2026-07-18T14:00:00Z",
      "expiration_value": "",
      "floor_strike": 87,
      "last_price_dollars": "0.0100",
      "latest_expiration_time": "2026-07-18T14:00:00Z",
      "liquidity_dollars": "0.0000",
      "market_type": "binary",
      "no_ask_dollars": "1.0000",
      "no_bid_dollars": "0.9900",
      "no_sub_title": "87\u00b0 to 88\u00b0",
      "notional_value_dollars": "1.0000",
      "occurrence_datetime": "2026-07-11T14:00:00Z",
      "open_interest_fp": "1446.26",
      "open_time": "2026-07-10T14:00:00Z",
      "previous_price_dollars": "0.0000",
      "previous_yes_ask_dollars": "0.0000",
      "previous_yes_bid_dollars": "0.0000",
      "price_level_structure": "linear_cent",
      "price_ranges": [
        {
          "end": "1.0000",
          "start": "0.0000",
          "step": "0.0100"
        }
      ],
      "result": "",
      "rules_primary": "If the highest temperature recorded in Central Park, New York for July 11, 2026 as reported by the National Weather Service's Climatological Report (Daily), is between 87-88\u00b0, then the market resolves to Yes.",
      "rules_secondary": "Not all weather data is the same. While checking a source like AccuWeather or Google Weather may help guide your decision, the official and final value used to determine this market is the highest temperature as reported by the corresponding NWS Climatological Report (Daily) linked in the rules above. Preliminary NWS reporting and measurement methods may be subject to underlying rounding and conversion nuances. Traders should exercise caution when interpreting preliminary NWS data.",
      "settlement_timer_seconds": 3600,
      "status": "active",
      "strike_type": "between",
      "subtitle": "87\u00b0 to 88\u00b0",
      "ticker": "KXHIGHNY-26JUL11-B87.5",
      "title": "Will the **high temp in NYC** be 87-88\u00b0 on Jul 11, 2026?",
      "updated_time": "2026-07-10T14:00:00.73332Z",
      "volume_24h_fp": "1637.26",
      "volume_fp": "1637.26",
      "yes_ask_dollars": "0.0100",
      "yes_ask_size_fp": "921.74",
      "yes_bid_dollars": "0.0000",
      "yes_bid_size_fp": "0.00",
      "yes_sub_title": "87\u00b0 to 88\u00b0"
    },
    {
      "can_close_early": true,
      "cap_strike": 86,
      "close_time": "2026-07-12T04:59:00Z",
      "created_time": "2026-07-10T09:30:32.382416Z",
      "early_close_condition": "The Last Trading Time will be 11:59 PM ET on July 11, 2026 regardless of any data releases or events occurring. Expiration will occur on the sooner of the first 7:00 or 8:00\nAM ET following the release of the data for July 11, 2026, or one week after July 11, 2026.",
      "event_ticker": "KXHIGHNY-26JUL11",
      "expected_expiration_time": "2026-07-12T14:00:00Z",
      "expiration_time": "2026-07-18T14:00:00Z",
      "expiration_value": "",
      "floor_strike": 85,
      "last_price_dollars": "0.0300",
      "latest_expiration_time": "2026-07-18T14:00:00Z",
      "liquidity_dollars": "0.0000",
      "market_type": "binary",
      "no_ask_dollars": "0.9700",
      "no_bid_dollars": "0.9600",
      "no_sub_title": "85\u00b0 to 86\u00b0",
      "notional_value_dollars": "1.0000",
      "occurrence_datetime": "2026-07-11T14:00:00Z",
      "open_interest_fp": "305.18",
      "open_time": "2026-07-10T14:00:00Z",
      "previous_price_dollars": "0.0000",
      "previous_yes_ask_dollars": "0.0000",
      "previous_yes_bid_dollars": "0.0000",
      "price_level_structure": "linear_cent",
      "price_ranges": [
        {
          "end": "1.0000",
          "start": "0.0000",
          "step": "0.0100"
        }
      ],
      "result": "",
      "rules_primary": "If the highest temperature recorded in Central Park, New York for July 11, 2026 as reported by the National Weather Service's Climatological Report (Daily), is between 85-86\u00b0, then the market resolves to Yes.",
      "rules_secondary": "Not all weather data is the same. While checking a source like AccuWeather or Google Weather may help guide your decision, the official and final value used to determine this market is the highest temperature as reported by the corresponding NWS Climatological Report (Daily) linked in the rules above. Preliminary NWS reporting and measurement methods may be subject to underlying rounding and conversion nuances. Traders should exercise caution when interpreting preliminary NWS data.",
      "settlement_timer_seconds": 3600,
      "status": "active",
      "strike_type": "between",
      "subtitle": "85\u00b0 to 86\u00b0",
      "ticker": "KXHIGHNY-26JUL11-B85.5",
      "title": "Will the **high temp in NYC** be 85-86\u00b0 on Jul 11, 2026?",
      "updated_time": "2026-07-10T14:00:00.73332Z",
      "volume_24h_fp": "359.19",
      "volume_fp": "365.19",
      "yes_ask_dollars": "0.0400",
      "yes_ask_size_fp": "124.20",
      "yes_bid_dollars": "0.0300",
      "yes_bid_size_fp": "87.00",
      "yes_sub_title": "85\u00b0 to 86\u00b0"
    },
    {
      "can_close_early": true,
      "cap_strike": 84,
      "close_time": "2026-07-12T04:59:00Z",
      "created_time": "2026-07-10T09:30:32.382416Z",
      "early_close_condition": "The Last Trading Time will be 11:59 PM ET on July 11, 2026 regardless of any data releases or events occurring. Expiration will occur on the sooner of the first 7:00 or 8:00\nAM ET following the release of the data for July 11, 2026, or one week after July 11, 2026.",
      "event_ticker": "KXHIGHNY-26JUL11",
      "expected_expiration_time": "2026-07-12T14:00:00Z",
      "expiration_time": "2026-07-18T14:00:00Z",
      "expiration_value": "",
      "floor_strike": 83,
      "last_price_dollars": "0.1100",
      "latest_expiration_time": "2026-07-18T14:00:00Z",
      "liquidity_dollars": "0.0000",
      "market_type": "binary",
      "no_ask_dollars": "0.9000",
      "no_bid_dollars": "0.8800",
      "no_sub_title": "83\u00b0 to 84\u00b0",
      "notional_value_dollars": "1.0000",
      "occurrence_datetime": "2026-07-11T14:00:00Z",
      "open_interest_fp": "821.31",
      "open_time": "2026-07-10T14:00:00Z",
      "previous_price_dollars": "0.0000",
      "previous_yes_ask_dollars": "0.0000",
      "previous_yes_bid_dollars": "0.0000",
      "price_level_structure": "linear_cent",
      "price_ranges": [
        {
          "end": "1.0000",
          "start": "0.0000",
          "step": "0.0100"
        }
      ],
      "result": "",
      "rules_primary": "If the highest temperature recorded in Central Park, New York for July 11, 2026 as reported by the National Weather Service's Climatological Report (Daily), is between 83-84\u00b0, then the market resolves to Yes.",
      "rules_secondary": "Not all weather data is the same. While checking a source like AccuWeather or Google Weather may help guide your decision, the official and final value used to determine this market is the highest temperature as reported by the corresponding NWS Climatological Report (Daily) linked in the rules above. Preliminary NWS reporting and measurement methods may be subject to underlying rounding and conversion nuances. Traders should exercise caution when interpreting preliminary NWS data.",
      "settlement_timer_seconds": 3600,
      "status": "active",
      "strike_type": "between",
      "subtitle": "83\u00b0 to 84\u00b0",
      "ticker": "KXHIGHNY-26JUL11-B83.5",
      "title": "Will the **high temp in NYC** be 83-84\u00b0 on Jul 11, 2026?",
      "updated_time": "2026-07-10T14:00:00.73332Z",
      "volume_24h_fp": "1055.29",
      "volume_fp": "1055.29",
      "yes_ask_dollars": "0.1200",
      "yes_ask_size_fp": "6.00",
      "yes_bid_dollars": "0.1000",
      "yes_bid_size_fp": "44.81",
      "yes_sub_title": "83\u00b0 to 84\u00b0"
    },
    {
      "can_close_early": true,
      "cap_strike": 82,
      "close_time": "2026-07-12T04:59:00Z",
      "created_time": "2026-07-10T09:30:32.382416Z",
      "early_close_condition": "The Last Trading Time will be 11:59 PM ET on July 11, 2026 regardless of any data releases or events occurring. Expiration will occur on the sooner of the first 7:00 or 8:00\nAM ET following the release of the data for July 11, 2026, or one week after July 11, 2026.",
      "event_ticker": "KXHIGHNY-26JUL11",
      "expected_expiration_time": "2026-07-12T14:00:00Z",
      "expiration_time": "2026-07-18T14:00:00Z",
      "expiration_value": "",
      "floor_strike": 81,
      "last_price_dollars": "0.2500",
      "latest_expiration_time": "2026-07-18T14:00:00Z",
      "liquidity_dollars": "0.0000",
      "market_type": "binary",
      "no_ask_dollars": "0.7600",
      "no_bid_dollars": "0.7500",
      "no_sub_title": "81\u00b0 to 82\u00b0",
      "notional_value_dollars": "1.0000",
      "occurrence_datetime": "2026-07-11T14:00:00Z",
      "open_interest_fp": "315.19",
      "open_time": "2026-07-10T14:00:00Z",
      "previous_price_dollars": "0.0000",
      "previous_yes_ask_dollars": "0.0000",
      "previous_yes_bid_dollars": "0.0000",
      "price_level_structure": "linear_cent",
      "price_ranges": [
        {
          "end": "1.0000",
          "start": "0.0000",
          "step": "0.0100"
        }
      ],
      "result": "",
      "rules_primary": "If the highest temperature recorded in Central Park, New York for July 11, 2026 as reported by the National Weather Service's Climatological Report (Daily), is between 81-82\u00b0, then the market resolves to Yes.",
      "rules_secondary": "Not all weather data is the same. While checking a source like AccuWeather or Google Weather may help guide your decision, the official and final value used to determine this market is the highest temperature as reported by the corresponding NWS Climatological Report (Daily) linked in the rules above. Preliminary NWS reporting and measurement methods may be subject to underlying rounding and conversion nuances. Traders should exercise caution when interpreting preliminary NWS data.",
      "settlement_timer_seconds": 3600,
      "status": "active",
      "strike_type": "between",
      "subtitle": "81\u00b0 to 82\u00b0",
      "ticker": "KXHIGHNY-26JUL11-B81.5",
      "title": "Will the **high temp in NYC** be 81-82\u00b0 on Jul 11, 2026?",
      "updated_time": "2026-07-10T14:00:00.73332Z",
      "volume_24h_fp": "381.64",
      "volume_fp": "381.64",
      "yes_ask_dollars": "0.2500",
      "yes_ask_size_fp": "181.00",
      "yes_bid_dollars": "0.2400",
      "yes_bid_size_fp": "48.62",
      "yes_sub_title": "81\u00b0 to 82\u00b0"
    },
    {
      "can_close_early": true,
      "close_time": "2026-07-11T04:59:00Z",
      "created_time": "2026-07-09T09:30:29.593795Z",
      "early_close_condition": "The Last Trading Time will be 11:59 PM ET on July 10, 2026 regardless of any data releases or events occurring. Expiration will occur on the sooner of the first 7:00 or 8:00\nAM ET following the release of the data for July 10, 2026, or one week after July 10, 2026.",
      "event_ticker": "KXHIGHNY-26JUL10",
      "expected_expiration_time": "2026-07-11T14:00:00Z",
      "expiration_time": "2026-07-17T14:00:00Z",
      "expiration_value": "",
      "floor_strike": 94,
      "last_price_dollars": "0.0100",
      "latest_expiration_time": "2026-07-17T14:00:00Z",
      "liquidity_dollars": "0.0000",
      "market_type": "binary",
      "no_ask_dollars": "1.0000",
      "no_bid_dollars": "0.9900",
      "no_sub_title": "95\u00b0 or above",
      "notional_value_dollars": "1.0000",
      "occurrence_datetime": "2026-07-10T14:00:00Z",
      "open_interest_fp": "3435.52",
      "open_time": "2026-07-09T14:00:00Z",
      "previous_price_dollars": "0.0100",
      "previous_yes_ask_dollars": "0.0200",
      "previous_yes_bid_dollars": "0.0100",
      "price_level_structure": "linear_cent",
      "price_ranges": [
        {
          "end": "1.0000",
          "start": "0.0000",
          "step": "0.0100"
        }
      ],
      "result": "",
      "rules_primary": "If the highest temperature recorded in Central Park, New York for July 10, 2026 as reported by the National Weather Service's Climatological Report (Daily), is greater than 94\u00b0, then the market resolves to Yes.",
      "rules_secondary": "Not all weather data is the same. While checking a source like AccuWeather or Google Weather may help guide your decision, the official and final value used to determine this market is the highest temperature as reported by the corresponding NWS Climatological Report (Daily) linked in the rules above. Preliminary NWS reporting and measurement methods may be subject to underlying rounding and conversion nuances. Traders should exercise caution when interpreting preliminary NWS data.",
      "settlement_timer_seconds": 3600,
      "status": "active",
      "strike_type": "greater",
      "subtitle": "95\u00b0 or above",
      "ticker": "KXHIGHNY-26JUL10-T94",
      "title": "Will the **high temp in NYC** be >94\u00b0 on Jul 10, 2026?",
      "updated_time": "2026-07-09T14:00:10.804019Z",
      "volume_24h_fp": "1729.52",
      "volume_fp": "3543.52",
      "yes_ask_dollars": "0.0100",
      "yes_ask_size_fp": "51848.85",
      "yes_bid_dollars": "0.0000",
      "yes_bid_size_fp": "0.00",
      "yes_sub_title": "95\u00b0 or above"
    },
    {
      "can_close_early": true,
      "cap_strike": 87,
      "close_time": "2026-07-11T04:59:00Z",
      "created_time": "2026-07-09T09:30:29.593795Z",
      "early_close_condition": "The Last Trading Time will be 11:59 PM ET on July 10, 2026 regardless of any data releases or events occurring. Expiration will occur on the sooner of the first 7:00 or 8:00\nAM ET following the release of the data for July 10, 2026, or one week after July 10, 2026.",
      "event_ticker": "KXHIGHNY-26JUL10",
      "expected_expiration_time": "2026-07-11T14:00:00Z",
      "expiration_time": "2026-07-17T14:00:00Z",
      "expiration_value": "",
      "last_price_dollars": "0.9600",
      "latest_expiration_time": "2026-07-17T14:00:00Z",
      "liquidity_dollars": "0.0000",
      "market_type": "binary",
      "no_ask_dollars": "0.0500",
      "no_bid_dollars": "0.0400",
      "no_sub_title": "86\u00b0 or below",
      "notional_value_dollars": "1.0000",
      "occurrence_datetime": "2026-07-10T14:00:00Z",
      "open_interest_fp": "18074.62",
      "open_time": "2026-07-09T14:00:00Z",
      "previous_price_dollars": "0.3600",
      "previous_yes_ask_dollars": "0.3600",
      "previous_yes_bid_dollars": "0.3400",
      "price_level_structure": "linear_cent",
      "price_ranges": [
        {
          "end": "1.0000",
          "start": "0.0000",
          "step": "0.0100"
        }
      ],
      "result": "",
      "rules_primary": "If the highest temperature recorded in Central Park, New York for July 10, 2026 as reported by the National Weather Service's Climatological Report (Daily), is less than 87\u00b0, then the market resolves to Yes.",
      "rules_secondary": "Not all weather data is the same. While checking a source like AccuWeather or Google Weather may help guide your decision, the official and final value used to determine this market is the highest temperature as reported by the corresponding NWS Climatological Report (Daily) linked in the rules above. Preliminary NWS reporting and measurement methods may be subject to underlying rounding and conversion nuances. Traders should exercise caution when interpreting preliminary NWS data.",
      "settlement_timer_seconds": 3600,
      "status": "active",
      "strike_type": "less",
      "subtitle": "86\u00b0 or below",
      "ticker": "KXHIGHNY-26JUL10-T87",
      "title": "Will the **high temp in NYC** be <87\u00b0 on Jul 10, 2026?",
      "updated_time": "2026-07-09T14:00:10.804019Z",
      "volume_24h_fp": "34597.31",
      "volume_fp": "35164.90",
      "yes_ask_dollars": "0.9600",
      "yes_ask_size_fp": "7.00",
      "yes_bid_dollars": "0.9500",
      "yes_bid_size_fp": "224.86",
      "yes_sub_title": "86\u00b0 or below"
    },
    {
      "can_close_early": true,
      "cap_strike": 94,
      "close_time": "2026-07-11T04:59:00Z",
      "created_time": "2026-07-09T09:30:29.593795Z",
      "early_close_condition": "The Last Trading Time will be 11:59 PM ET on July 10, 2026 regardless of any data releases or events occurring. Expiration will occur on the sooner of the first 7:00 or 8:00\nAM ET following the release of the data for July 10, 2026, or one week after July 10, 2026.",
      "event_ticker": "KXHIGHNY-26JUL10",
      "expected_expiration_time": "2026-07-11T14:00:00Z",
      "expiration_time": "2026-07-17T14:00:00Z",
      "expiration_value": "",
      "floor_strike": 93,
      "last_price_dollars": "0.0100",
      "latest_expiration_time": "2026-07-17T14:00:00Z",
      "liquidity_dollars": "0.0000",
      "market_type": "binary",
      "no_ask_dollars": "1.0000",
      "no_bid_dollars": "0.9900",
      "no_sub_title": "93\u00b0 to 94\u00b0",
      "notional_value_dollars": "1.0000",
      "occurrence_datetime": "2026-07-10T14:00:00Z",
      "open_interest_fp": "1880.62",
      "open_time": "2026-07-09T14:00:00Z",
      "previous_price_dollars": "0.0400",
      "previous_yes_ask_dollars": "0.0400",
      "previous_yes_bid_dollars": "0.0200",
      "price_level_structure": "linear_cent",
      "price_ranges": [
        {
          "end": "1.0000",
          "start": "0.0000",
          "step": "0.0100"
        }
      ],
      "result": "",
      "rules_primary": "If the highest temperature recorded in Central Park, New York for July 10, 2026 as reported by the National Weather Service's Climatological Report (Daily), is between 93-94\u00b0, then the market resolves to Yes.",
      "rules_secondary": "Not all weather data is the same. While checking a source like AccuWeather or Google Weather may help guide your decision, the official and final value used to determine this market is the highest temperature as reported by the corresponding NWS Climatological Report (Daily) linked in the rules above. Preliminary NWS reporting and measurement methods may be subject to underlying rounding and conversion nuances. Traders should exercise caution when interpreting preliminary NWS data.",
      "settlement_timer_seconds": 3600,
      "status": "active",
      "strike_type": "between",
      "subtitle": "93\u00b0 to 94\u00b0",
      "ticker": "KXHIGHNY-26JUL10-B93.5",
      "title": "Will the **high temp in NYC** be 93-94\u00b0 on Jul 10, 2026?",
      "updated_time": "2026-07-09T14:00:10.804019Z",
      "volume_24h_fp": "1827.40",
      "volume_fp": "1898.62",
      "yes_ask_dollars": "0.0100",
      "yes_ask_size_fp": "43657.97",
      "yes_bid_dollars": "0.0000",
      "yes_bid_size_fp": "0.00",
      "yes_sub_title": "93\u00b0 to 94\u00b0"
    },
    {
      "can_close_early": true,
      "cap_strike": 92,
      "close_time": "2026-07-11T04:59:00Z",
      "created_time": "2026-07-09T09:30:29.593795Z",
      "early_close_condition": "The Last Trading Time will be 11:59 PM ET on July 10, 2026 regardless of any data releases or events occurring. Expiration will occur on the sooner of the first 7:00 or 8:00\nAM ET following the release of the data for July 10, 2026, or one week after July 10, 2026.",
      "event_ticker": "KXHIGHNY-26JUL10",
      "expected_expiration_time": "2026-07-11T14:00:00Z",
      "expiration_time": "2026-07-17T14:00:00Z",
      "expiration_value": "",
      "floor_strike": 91,
      "last_price_dollars": "0.0100",
      "latest_expiration_time": "2026-07-17T14:00:00Z",
      "liquidity_dollars": "0.0000",
      "market_type": "binary",
      "no_ask_dollars": "1.0000",
      "no_bid_dollars": "0.9900",
      "no_sub_title": "91\u00b0 to 92\u00b0",
      "notional_value_dollars": "1.0000",
      "occurrence_datetime": "2026-07-10T14:00:00Z",
      "open_interest_fp": "4026.21",
      "open_time": "2026-07-09T14:00:00Z",
      "previous_price_dollars": "0.0900",
      "previous_yes_ask_dollars": "0.0800",
      "previous_yes_bid_dollars": "0.0600",
      "price_level_structure": "linear_cent",
      "price_ranges": [
        {
          "end": "1.0000",
          "start": "0.0000",
          "step": "0.0100"
        }
      ],
      "result": "",
      "rules_primary": "If the highest temperature recorded in Central Park, New York for July 10, 2026 as reported by the National Weather Service's Climatological Report (Daily), is between 91-92\u00b0, then the market resolves to Yes.",
      "rules_secondary": "Not all weather data is the same. While checking a source like AccuWeather or Google Weather may help guide your decision, the official and final value used to determine this market is the highest temperature as reported by the corresponding NWS Climatological Report (Daily) linked in the rules above. Preliminary NWS reporting and measurement methods may be subject to underlying rounding and conversion nuances. Traders should exercise caution when interpreting preliminary NWS data.",
      "settlement_timer_seconds": 3600,
      "status": "active",
      "strike_type": "between",
      "subtitle": "91\u00b0 to 92\u00b0",
      "ticker": "KXHIGHNY-26JUL10-B91.5",
      "title": "Will the **high temp in NYC** be 91-92\u00b0 on Jul 10, 2026?",
      "updated_time": "2026-07-09T14:00:10.804019Z",
      "volume_24h_fp": "4484.89",
      "volume_fp": "4542.88",
      "yes_ask_dollars": "0.0100",
      "yes_ask_size_fp": "42607.40",
      "yes_bid_dollars": "0.0000",
      "yes_bid_size_fp": "0.00",
      "yes_sub_title": "91\u00b0 to 92\u00b0"
    },
    {
      "can_close_early": true,
      "cap_strike": 90,
      "close_time": "2026-07-11T04:59:00Z",
      "created_time": "2026-07-09T09:30:29.593795Z",
      "early_close_condition": "The Last Trading Time will be 11:59 PM ET on July 10, 2026 regardless of any data releases or events occurring. Expiration will occur on the sooner of the first 7:00 or 8:00\nAM ET following the release of the data for July 10, 2026, or one week after July 10, 2026.",
      "event_ticker": "KXHIGHNY-26JUL10",
      "expected_expiration_time": "2026-07-11T14:00:00Z",
      "expiration_time": "2026-07-17T14:00:00Z",
      "expiration_value": "",
      "floor_strike": 89,
      "last_price_dollars": "0.0100",
      "latest_expiration_time": "2026-07-17T14:00:00Z",
      "liquidity_dollars": "0.0000",
      "market_type": "binary",
      "no_ask_dollars": "1.0000",
      "no_bid_dollars": "0.9900",
      "no_sub_title": "89\u00b0 to 90\u00b0",
      "notional_value_dollars": "1.0000",
      "occurrence_datetime": "2026-07-10T14:00:00Z",
      "open_interest_fp": "13954.04",
      "open_time": "2026-07-09T14:00:00Z",
      "previous_price_dollars": "0.2900",
      "previous_yes_ask_dollars": "0.2900",
      "previous_yes_bid_dollars": "0.2700",
      "price_level_structure": "linear_cent",
      "price_ranges": [
        {
          "end": "1.0000",
          "start": "0.0000",
          "step": "0.0100"
        }
      ],
      "result": "",
      "rules_primary": "If the highest temperature recorded in Central Park, New York for July 10, 2026 as reported by the National Weather Service's Climatological Report (Daily), is between 89-90\u00b0, then the market resolves to Yes.",
      "rules_secondary": "Not all weather data is the same. While checking a source like AccuWeather or Google Weather may help guide your decision, the official and final value used to determine this market is the highest temperature as reported by the corresponding NWS Climatological Report (Daily) linked in the rules above. Preliminary NWS reporting and measurement methods may be subject to underlying rounding and conversion nuances. Traders should exercise caution when interpreting preliminary NWS data.",
      "settlement_timer_seconds": 3600,
      "status": "active",
      "strike_type": "between",
      "subtitle": "89\u00b0 to 90\u00b0",
      "ticker": "KXHIGHNY-26JUL10-B89.5",
      "title": "Will the **high temp in NYC** be 89-90\u00b0 on Jul 10, 2026?",
      "updated_time": "2026-07-09T14:00:10.804019Z",
      "volume_24h_fp": "16012.51",
      "volume_fp": "18643.71",
      "yes_ask_dollars": "0.0100",
      "yes_ask_size_fp": "36269.43",
      "yes_bid_dollars": "0.0000",
      "yes_bid_size_fp": "0.00",
      "yes_sub_title": "89\u00b0 to 90\u00b0"
    },
    {
      "can_close_early": true,
      "cap_strike": 88,
      "close_time": "2026-07-11T04:59:00Z",
      "created_time": "2026-07-09T09:30:29.593795Z",
      "early_close_condition": "The Last Trading Time will be 11:59 PM ET on July 10, 2026 regardless of any data releases or events occurring. Expiration will occur on the sooner of the first 7:00 or 8:00\nAM ET following the release of the data for July 10, 2026, or one week after July 10, 2026.",
      "event_ticker": "KXHIGHNY-26JUL10",
      "expected_expiration_time": "2026-07-11T14:00:00Z",
      "expiration_time": "2026-07-17T14:00:00Z",
      "expiration_value": "",
      "floor_strike": 87,
      "last_price_dollars": "0.0300",
      "latest_expiration_time": "2026-07-17T14:00:00Z",
      "liquidity_dollars": "0.0000",
      "market_type": "binary",
      "no_ask_dollars": "0.9700",
      "no_bid_dollars": "0.9500",
      "no_sub_title": "87\u00b0 to 88\u00b0",
      "notional_value_dollars": "1.0000",
      "occurrence_datetime": "2026-07-10T14:00:00Z",
      "open_interest_fp": "16125.22",
      "open_time": "2026-07-09T14:00:00Z",
      "previous_price_dollars": "0.3000",
      "previous_yes_ask_dollars": "0.3000",
      "previous_yes_bid_dollars": "0.2900",
      "price_level_structure": "linear_cent",
      "price_ranges": [
        {
          "end": "1.0000",
          "start": "0.0000",
          "step": "0.0100"
        }
      ],
      "result": "",
      "rules_primary": "If the highest temperature recorded in Central Park, New York for July 10, 2026 as reported by the National Weather Service's Climatological Report (Daily), is between 87-88\u00b0, then the market resolves to Yes.",
      "rules_secondary": "Not all weather data is the same. While checking a source like AccuWeather or Google Weather may help guide your decision, the official and final value used to determine this market is the highest temperature as reported by the corresponding NWS Climatological Report (Daily) linked in the rules above. Preliminary NWS reporting and measurement methods may be subject to underlying rounding and conversion nuances. Traders should exercise caution when interpreting preliminary NWS data.",
      "settlement_timer_seconds": 3600,
      "status": "active",
      "strike_type": "between",
      "subtitle": "87\u00b0 to 88\u00b0",
      "ticker": "KXHIGHNY-26JUL10-B87.5",
      "title": "Will the **high temp in NYC** be 87-88\u00b0 on Jul 10, 2026?",
      "updated_time": "2026-07-09T14:00:10.804019Z",
      "volume_24h_fp": "25381.94",
      "volume_fp": "27214.36",
      "yes_ask_dollars": "0.0500",
      "yes_ask_size_fp": "51.00",
      "yes_bid_dollars": "0.0300",
      "yes_bid_size_fp": "16.00",
      "yes_sub_title": "87\u00b0 to 88\u00b0"
    }
  ],
  "cursor": null
}