{
  "fetchedAt": "2026-06-22T23:48:54Z",
  "series": "KXHIGHNY",
  "markets": [
    {
      "can_close_early": true,
      "close_time": "2026-06-24T04:59:00Z",
      "created_time": "2026-06-22T09:30:27.239441Z",
      "early_close_condition": "The Last Trading Time will be 11:59 PM ET on June 23, 2026 regardless of any data releases or events occurring. Expiration will occur on the sooner of the first 7:00 or 8:00\nAM ET following the release of the data for June 23, 2026, or one week after June 23, 2026.",
      "event_ticker": "KXHIGHNY-26JUN23",
      "expected_expiration_time": "2026-06-24T14:00:00Z",
      "expiration_time": "2026-06-30T14:00:00Z",
      "expiration_value": "",
      "floor_strike": 85,
      "fractional_trading_enabled": true,
      "last_price_dollars": "0.0100",
      "latest_expiration_time": "2026-06-30T14:00:00Z",
      "liquidity_dollars": "0.0000",
      "market_type": "binary",
      "no_ask_dollars": "1.0000",
      "no_bid_dollars": "0.9900",
      "no_sub_title": "86\u00b0 or above",
      "notional_value_dollars": "1.0000",
      "occurrence_datetime": "2026-06-23T14:00:00Z",
      "open_interest_fp": "1089.00",
      "open_time": "2026-06-22T14:00:00Z",
      "previous_price_dollars": "0.0000",
      "previous_yes_ask_dollars": "0.0000",
      "previous_yes_bid_dollars": "0.0000",
      "price_level_structure": "linear_cent",
      "price_ranges": [
        {
          "end": "1.0000",
          "start": "0.0000",
          "step": "0.0100"
        }
      ],
      "response_price_units": "usd_cent",
      "result": "",
      "rules_primary": "If the highest temperature recorded in Central Park, New York for June 23, 2026 as reported by the National Weather Service's Climatological Report (Daily), is greater than 85\u00b0, then the market resolves to Yes.",
      "rules_secondary": "Not all weather data is the same. While checking a source like AccuWeather or Google Weather may help guide your decision, the official and final value used to determine this market is the highest temperature as reported by the corresponding NWS Climatological Report (Daily) linked in the rules above. Preliminary NWS reporting and measurement methods may be subject to underlying rounding and conversion nuances. Traders should exercise caution when interpreting preliminary NWS data.",
      "settlement_timer_seconds": 3600,
      "status": "active",
      "strike_type": "greater",
      "subtitle": "86\u00b0 or above",
      "ticker": "KXHIGHNY-26JUN23-T85",
      "title": "Will the **high temp in NYC** be >85\u00b0 on Jun 23, 2026?",
      "updated_time": "2026-06-22T14:00:00.170401Z",
      "volume_24h_fp": "1323.00",
      "volume_fp": "1323.00",
      "yes_ask_dollars": "0.0100",
      "yes_ask_size_fp": "1834.00",
      "yes_bid_dollars": "0.0000",
      "yes_bid_size_fp": "0.00",
      "yes_sub_title": "86\u00b0 or above"
    },
    {
      "can_close_early": true,
      "cap_strike": 78,
      "close_time": "2026-06-24T04:59:00Z",
      "created_time": "2026-06-22T09:30:27.239441Z",
      "early_close_condition": "The Last Trading Time will be 11:59 PM ET on June 23, 2026 regardless of any data releases or events occurring. Expiration will occur on the sooner of the first 7:00 or 8:00\nAM ET following the release of the data for June 23, 2026, or one week after June 23, 2026.",
      "event_ticker": "KXHIGHNY-26JUN23",
      "expected_expiration_time": "2026-06-24T14:00:00Z",
      "expiration_time": "2026-06-30T14:00:00Z",
      "expiration_value": "",
      "fractional_trading_enabled": true,
      "last_price_dollars": "0.9200",
      "latest_expiration_time": "2026-06-30T14:00:00Z",
      "liquidity_dollars": "0.0000",
      "market_type": "binary",
      "no_ask_dollars": "0.0900",
      "no_bid_dollars": "0.0800",
      "no_sub_title": "77\u00b0 or below",
      "notional_value_dollars": "1.0000",
      "occurrence_datetime": "2026-06-23T14:00:00Z",
      "open_interest_fp": "1303.94",
      "open_time": "2026-06-22T14:00:00Z",
      "previous_price_dollars": "0.0000",
      "previous_yes_ask_dollars": "0.0000",
      "previous_yes_bid_dollars": "0.0000",
      "price_level_structure": "linear_cent",
      "price_ranges": [
        {
          "end": "1.0000",
          "start": "0.0000",
          "step": "0.0100"
        }
      ],
      "response_price_units": "usd_cent",
      "result": "",
      "rules_primary": "If the highest temperature recorded in Central Park, New York for June 23, 2026 as reported by the National Weather Service's Climatological Report (Daily), is less than 78\u00b0, then the market resolves to Yes.",
      "rules_secondary": "Not all weather data is the same. While checking a source like AccuWeather or Google Weather may help guide your decision, the official and final value used to determine this market is the highest temperature as reported by the corresponding NWS Climatological Report (Daily) linked in the rules above. Preliminary NWS reporting and measurement methods may be subject to underlying rounding and conversion nuances. Traders should exercise caution when interpreting preliminary NWS data.",
      "settlement_timer_seconds": 3600,
      "status": "active",
      "strike_type": "less",
      "subtitle": "77\u00b0 or below",
      "ticker": "KXHIGHNY-26JUN23-T78",
      "title": "Will the **high temp in NYC** be <78\u00b0 on Jun 23, 2026?",
      "updated_time": "2026-06-22T14:00:00.170401Z",
      "volume_24h_fp": "1569.06",
      "volume_fp": "1569.06",
      "yes_ask_dollars": "0.9200",
      "yes_ask_size_fp": "85.00",
      "yes_bid_dollars": "0.9100",
      "yes_bid_size_fp": "572.00",
      "yes_sub_title": "77\u00b0 or below"
    },
    {
      "can_close_early": true,
      "cap_strike": 85,
      "close_time": "2026-06-24T04:59:00Z",
      "created_time": "2026-06-22T09:30:27.239441Z",
      "early_close_condition": "The Last Trading Time will be 11:59 PM ET on June 23, 2026 regardless of any data releases or events occurring. Expiration will occur on the sooner of the first 7:00 or 8:00\nAM ET following the release of the data for June 23, 2026, or one week after June 23, 2026.",
      "event_ticker": "KXHIGHNY-26JUN23",
      "expected_expiration_time": "2026-06-24T14:00:00Z",
      "expiration_time": "2026-06-30T14:00:00Z",
      "expiration_value": "",
      "floor_strike": 84,
      "fractional_trading_enabled": true,
      "last_price_dollars": "0.0100",
      "latest_expiration_time": "2026-06-30T14:00:00Z",
      "liquidity_dollars": "0.0000",
      "market_type": "binary",
      "no_ask_dollars": "1.0000",
      "no_bid_dollars": "0.9800",
      "no_sub_title": "84\u00b0 to 85\u00b0",
      "notional_value_dollars": "1.0000",
      "occurrence_datetime": "2026-06-23T14:00:00Z",
      "open_interest_fp": "1350.50",
      "open_time": "2026-06-22T14:00:00Z",
      "previous_price_dollars": "0.0000",
      "previous_yes_ask_dollars": "0.0000",
      "previous_yes_bid_dollars": "0.0000",
      "price_level_structure": "linear_cent",
      "price_ranges": [
        {
          "end": "1.0000",
          "start": "0.0000",
          "step": "0.0100"
        }
      ],
      "response_price_units": "usd_cent",
      "result": "",
      "rules_primary": "If the highest temperature recorded in Central Park, New York for June 23, 2026 as reported by the National Weather Service's Climatological Report (Daily), is between 84-85\u00b0, then the market resolves to Yes.",
      "rules_secondary": "Not all weather data is the same. While checking a source like AccuWeather or Google Weather may help guide your decision, the official and final value used to determine this market is the highest temperature as reported by the corresponding NWS Climatological Report (Daily) linked in the rules above. Preliminary NWS reporting and measurement methods may be subject to underlying rounding and conversion nuances. Traders should exercise caution when interpreting preliminary NWS data.",
      "settlement_timer_seconds": 3600,
      "status": "active",
      "strike_type": "between",
      "subtitle": "84\u00b0 to 85\u00b0",
      "ticker": "KXHIGHNY-26JUN23-B84.5",
      "title": "Will the **high temp in NYC** be 84-85\u00b0 on Jun 23, 2026?",
      "updated_time": "2026-06-22T14:00:00.170401Z",
      "volume_24h_fp": "1470.50",
      "volume_fp": "1470.50",
      "yes_ask_dollars": "0.0200",
      "yes_ask_size_fp": "89.00",
      "yes_bid_dollars": "0.0000",
      "yes_bid_size_fp": "0.00",
      "yes_sub_title": "84\u00b0 to 85\u00b0"
    },
    {
      "can_close_early": true,
      "cap_strike": 83,
      "close_time": "2026-06-24T04:59:00Z",
      "created_time": "2026-06-22T09:30:27.239441Z",
      "early_close_condition": "The Last Trading Time will be 11:59 PM ET on June 23, 2026 regardless of any data releases or events occurring. Expiration will occur on the sooner of the first 7:00 or 8:00\nAM ET following the release of the data for June 23, 2026, or one week after June 23, 2026.",
      "event_ticker": "KXHIGHNY-26JUN23",
      "expected_expiration_time": "2026-06-24T14:00:00Z",
      "expiration_time": "2026-06-30T14:00:00Z",
      "expiration_value": "",
      "floor_strike": 82,
      "fractional_trading_enabled": true,
      "last_price_dollars": "0.0200",
      "latest_expiration_time": "2026-06-30T14:00:00Z",
      "liquidity_dollars": "0.0000",
      "market_type": "binary",
      "no_ask_dollars": "0.9900",
      "no_bid_dollars": "0.9800",
      "no_sub_title": "82\u00b0 to 83\u00b0",
      "notional_value_dollars": "1.0000",
      "occurrence_datetime": "2026-06-23T14:00:00Z",
      "open_interest_fp": "1053.00",
      "open_time": "2026-06-22T14:00:00Z",
      "previous_price_dollars": "0.0000",
      "previous_yes_ask_dollars": "0.0000",
      "previous_yes_bid_dollars": "0.0000",
      "price_level_structure": "linear_cent",
      "price_ranges": [
        {
          "end": "1.0000",
          "start": "0.0000",
          "step": "0.0100"
        }
      ],
      "response_price_units": "usd_cent",
      "result": "",
      "rules_primary": "If the highest temperature recorded in Central Park, New York for June 23, 2026 as reported by the National Weather Service's Climatological Report (Daily), is between 82-83\u00b0, then the market resolves to Yes.",
      "rules_secondary": "Not all weather data is the same. While checking a source like AccuWeather or Google Weather may help guide your decision, the official and final value used to determine this market is the highest temperature as reported by the corresponding NWS Climatological Report (Daily) linked in the rules above. Preliminary NWS reporting and measurement methods may be subject to underlying rounding and conversion nuances. Traders should exercise caution when interpreting preliminary NWS data.",
      "settlement_timer_seconds": 3600,
      "status": "active",
      "strike_type": "between",
      "subtitle": "82\u00b0 to 83\u00b0",
      "ticker": "KXHIGHNY-26JUN23-B82.5",
      "title": "Will the **high temp in NYC** be 82-83\u00b0 on Jun 23, 2026?",
      "updated_time": "2026-06-22T14:00:00.170401Z",
      "volume_24h_fp": "1274.00",
      "volume_fp": "1274.00",
      "yes_ask_dollars": "0.0200",
      "yes_ask_size_fp": "214.00",
      "yes_bid_dollars": "0.0100",
      "yes_bid_size_fp": "39.00",
      "yes_sub_title": "82\u00b0 to 83\u00b0"
    },
    {
      "can_close_early": true,
      "cap_strike": 81,
      "close_time": "2026-06-24T04:59:00Z",
      "created_time": "2026-06-22T09:30:27.239441Z",
      "early_close_condition": "The Last Trading Time will be 11:59 PM ET on June 23, 2026 regardless of any data releases or events occurring. Expiration will occur on the sooner of the first 7:00 or 8:00\nAM ET following the release of the data for June 23, 2026, or one week after June 23, 2026.",
      "event_ticker": "KXHIGHNY-26JUN23",
      "expected_expiration_time": "2026-06-24T14:00:00Z",
      "expiration_time": "2026-06-30T14:00:00Z",
      "expiration_value": "",
      "floor_strike": 80,
      "fractional_trading_enabled": true,
      "last_price_dollars": "0.0100",
      "latest_expiration_time": "2026-06-30T14:00:00Z",
      "liquidity_dollars": "0.0000",
      "market_type": "binary",
      "no_ask_dollars": "0.9900",
      "no_bid_dollars": "0.9700",
      "no_sub_title": "80\u00b0 to 81\u00b0",
      "notional_value_dollars": "1.0000",
      "occurrence_datetime": "2026-06-23T14:00:00Z",
      "open_interest_fp": "1901.41",
      "open_time": "2026-06-22T14:00:00Z",
      "previous_price_dollars": "0.0000",
      "previous_yes_ask_dollars": "0.0000",
      "previous_yes_bid_dollars": "0.0000",
      "price_level_structure": "linear_cent",
      "price_ranges": [
        {
          "end": "1.0000",
          "start": "0.0000",
          "step": "0.0100"
        }
      ],
      "response_price_units": "usd_cent",
      "result": "",
      "rules_primary": "If the highest temperature recorded in Central Park, New York for June 23, 2026 as reported by the National Weather Service's Climatological Report (Daily), is between 80-81\u00b0, then the market resolves to Yes.",
      "rules_secondary": "Not all weather data is the same. While checking a source like AccuWeather or Google Weather may help guide your decision, the official and final value used to determine this market is the highest temperature as reported by the corresponding NWS Climatological Report (Daily) linked in the rules above. Preliminary NWS reporting and measurement methods may be subject to underlying rounding and conversion nuances. Traders should exercise caution when interpreting preliminary NWS data.",
      "settlement_timer_seconds": 3600,
      "status": "active",
      "strike_type": "between",
      "subtitle": "80\u00b0 to 81\u00b0",
      "ticker": "KXHIGHNY-26JUN23-B80.5",
      "title": "Will the **high temp in NYC** be 80-81\u00b0 on Jun 23, 2026?",
      "updated_time": "2026-06-22T14:00:00.170401Z",
      "volume_24h_fp": "2624.01",
      "volume_fp": "2624.01",
      "yes_ask_dollars": "0.0300",
      "yes_ask_size_fp": "107.00",
      "yes_bid_dollars": "0.0100",
      "yes_bid_size_fp": "2129.58",
      "yes_sub_title": "80\u00b0 to 81\u00b0"
    },
    {
      "can_close_early": true,
      "cap_strike": 79,
      "close_time": "2026-06-24T04:59:00Z",
      "created_time": "2026-06-22T09:30:27.239441Z",
      "early_close_condition": "The Last Trading Time will be 11:59 PM ET on June 23, 2026 regardless of any data releases or events occurring. Expiration will occur on the sooner of the first 7:00 or 8:00\nAM ET following the release of the data for June 23, 2026, or one week after June 23, 2026.",
      "event_ticker": "KXHIGHNY-26JUN23",
      "expected_expiration_time": "2026-06-24T14:00:00Z",
      "expiration_time": "2026-06-30T14:00:00Z",
      "expiration_value": "",
      "floor_strike": 78,
      "fractional_trading_enabled": true,
      "last_price_dollars": "0.0700",
      "latest_expiration_time": "2026-06-30T14:00:00Z",
      "liquidity_dollars": "0.0000",
      "market_type": "binary",
      "no_ask_dollars": "0.9500",
      "no_bid_dollars": "0.9300",
      "no_sub_title": "78\u00b0 to 79\u00b0",
      "notional_value_dollars": "1.0000",
      "occurrence_datetime": "2026-06-23T14:00:00Z",
      "open_interest_fp": "1006.53",
      "open_time": "2026-06-22T14:00:00Z",
      "previous_price_dollars": "0.0000",
      "previous_yes_ask_dollars": "0.0000",
      "previous_yes_bid_dollars": "0.0000",
      "price_level_structure": "linear_cent",
      "price_ranges": [
        {
          "end": "1.0000",
          "start": "0.0000",
          "step": "0.0100"
        }
      ],
      "response_price_units": "usd_cent",
      "result": "",
      "rules_primary": "If the highest temperature recorded in Central Park, New York for June 23, 2026 as reported by the National Weather Service's Climatological Report (Daily), is between 78-79\u00b0, then the market resolves to Yes.",
      "rules_secondary": "Not all weather data is the same. While checking a source like AccuWeather or Google Weather may help guide your decision, the official and final value used to determine this market is the highest temperature as reported by the corresponding NWS Climatological Report (Daily) linked in the rules above. Preliminary NWS reporting and measurement methods may be subject to underlying rounding and conversion nuances. Traders should exercise caution when interpreting preliminary NWS data.",
      "settlement_timer_seconds": 3600,
      "status": "active",
      "strike_type": "between",
      "subtitle": "78\u00b0 to 79\u00b0",
      "ticker": "KXHIGHNY-26JUN23-B78.5",
      "title": "Will the **high temp in NYC** be 78-79\u00b0 on Jun 23, 2026?",
      "updated_time": "2026-06-22T14:00:00.301706Z",
      "volume_24h_fp": "1361.09",
      "volume_fp": "1361.09",
      "yes_ask_dollars": "0.0700",
      "yes_ask_size_fp": "6.00",
      "yes_bid_dollars": "0.0500",
      "yes_bid_size_fp": "101.00",
      "yes_sub_title": "78\u00b0 to 79\u00b0"
    },
    {
      "can_close_early": true,
      "close_time": "2026-06-23T04:59:00Z",
      "created_time": "2026-06-21T09:30:41.967743Z",
      "early_close_condition": "The Last Trading Time will be 11:59 PM ET on June 22, 2026 regardless of any data releases or events occurring. Expiration will occur on the sooner of the first 7:00 or 8:00\nAM ET following the release of the data for June 22, 2026, or one week after June 22, 2026.",
      "event_ticker": "KXHIGHNY-26JUN22",
      "expected_expiration_time": "2026-06-23T14:00:00Z",
      "expiration_time": "2026-06-29T14:00:00Z",
      "expiration_value": "",
      "floor_strike": 79,
      "fractional_trading_enabled": true,
      "last_price_dollars": "0.0100",
      "latest_expiration_time": "2026-06-29T14:00:00Z",
      "liquidity_dollars": "0.0000",
      "market_type": "binary",
      "no_ask_dollars": "1.0000",
      "no_bid_dollars": "0.9900",
      "no_sub_title": "80\u00b0 or above",
      "notional_value_dollars": "1.0000",
      "occurrence_datetime": "2026-06-22T14:00:00Z",
      "open_interest_fp": "26029.98",
      "open_time": "2026-06-21T14:00:00Z",
      "previous_price_dollars": "0.0300",
      "previous_yes_ask_dollars": "0.0300",
      "previous_yes_bid_dollars": "0.0200",
      "price_level_structure": "linear_cent",
      "price_ranges": [
        {
          "end": "1.0000",
          "start": "0.0000",
          "step": "0.0100"
        }
      ],
      "response_price_units": "usd_cent",
      "result": "",
      "rules_primary": "If the highest temperature recorded in Central Park, New York for June 22, 2026 as reported by the National Weather Service's Climatological Report (Daily), is greater than 79\u00b0, then the market resolves to Yes.",
      "rules_secondary": "Not all weather data is the same. While checking a source like AccuWeather or Google Weather may help guide your decision, the official and final value used to determine this market is the highest temperature as reported by the corresponding NWS Climatological Report (Daily) linked in the rules above. Preliminary NWS reporting and measurement methods may be subject to underlying rounding and conversion nuances. Traders should exercise caution when interpreting preliminary NWS data.",
      "settlement_timer_seconds": 3600,
      "status": "active",
      "strike_type": "greater",
      "subtitle": "80\u00b0 or above",
      "ticker": "KXHIGHNY-26JUN22-T79",
      "title": "Will the **high temp in NYC** be >79\u00b0 on Jun 22, 2026?",
      "updated_time": "2026-06-21T14:00:00.557958Z",
      "volume_24h_fp": "27845.43",
      "volume_fp": "29147.60",
      "yes_ask_dollars": "0.0100",
      "yes_ask_size_fp": "33302.88",
      "yes_bid_dollars": "0.0000",
      "yes_bid_size_fp": "0.00",
      "yes_sub_title": "80\u00b0 or above"
    },
    {
      "can_close_early": true,
      "cap_strike": 72,
      "close_time": "2026-06-23T04:59:00Z",
      "created_time": "2026-06-21T09:30:41.967743Z",
      "early_close_condition": "The Last Trading Time will be 11:59 PM ET on June 22, 2026 regardless of any data releases or events occurring. Expiration will occur on the sooner of the first 7:00 or 8:00\nAM ET following the release of the data for June 22, 2026, or one week after June 22, 2026.",
      "event_ticker": "KXHIGHNY-26JUN22",
      "expected_expiration_time": "2026-06-23T14:00:00Z",
      "expiration_time": "2026-06-29T14:00:00Z",
      "expiration_value": "",
      "fractional_trading_enabled": true,
      "last_price_dollars": "0.0100",
      "latest_expiration_time": "2026-06-29T14:00:00Z",
      "liquidity_dollars": "0.0000",
      "market_type": "binary",
      "no_ask_dollars": "1.0000",
      "no_bid_dollars": "0.9900",
      "no_sub_title": "71\u00b0 or below",
      "notional_value_dollars": "1.0000",
      "occurrence_datetime": "2026-06-22T14:00:00Z",
      "open_interest_fp": "9142.10",
      "open_time": "2026-06-21T14:00:00Z",
      "previous_price_dollars": "0.0600",
      "previous_yes_ask_dollars": "0.0600",
      "previous_yes_bid_dollars": "0.0500",
      "price_level_structure": "linear_cent",
      "price_ranges": [
        {
          "end": "1.0000",
          "start": "0.0000",
          "step": "0.0100"
        }
      ],
      "response_price_units": "usd_cent",
      "result": "",
      "rules_primary": "If the highest temperature recorded in Central Park, New York for June 22, 2026 as reported by the National Weather Service's Climatological Report (Daily), is less than 72\u00b0, then the market resolves to Yes.",
      "rules_secondary": "Not all weather data is the same. While checking a source like AccuWeather or Google Weather may help guide your decision, the official and final value used to determine this market is the highest temperature as reported by the corresponding NWS Climatological Report (Daily) linked in the rules above. Preliminary NWS reporting and measurement methods may be subject to underlying rounding and conversion nuances. Traders should exercise caution when interpreting preliminary NWS data.",
      "settlement_timer_seconds": 3600,
      "status": "active",
      "strike_type": "less",
      "subtitle": "71\u00b0 or below",
      "ticker": "KXHIGHNY-26JUN22-T72",
      "title": "Will the **high temp in NYC** be <72\u00b0 on Jun 22, 2026?",
      "updated_time": "2026-06-21T14:00:00.557958Z",
      "volume_24h_fp": "9053.68",
      "volume_fp": "10527.98",
      "yes_ask_dollars": "0.0100",
      "yes_ask_size_fp": "373813.02",
      "yes_bid_dollars": "0.0000",
      "yes_bid_size_fp": "0.00",
      "yes_sub_title": "71\u00b0 or below"
    },
    {
      "can_close_early": true,
      "cap_strike": 79,
      "close_time": "2026-06-23T04:59:00Z",
      "created_time": "2026-06-21T09:30:41.967743Z",
      "early_close_condition": "The Last Trading Time will be 11:59 PM ET on June 22, 2026 regardless of any data releases or events occurring. Expiration will occur on the sooner of the first 7:00 or 8:00\nAM ET following the release of the data for June 22, 2026, or one week after June 22, 2026.",
      "event_ticker": "KXHIGHNY-26JUN22",
      "expected_expiration_time": "2026-06-23T14:00:00Z",
      "expiration_time": "2026-06-29T14:00:00Z",
      "expiration_value": "",
      "floor_strike": 78,
      "fractional_trading_enabled": true,
      "last_price_dollars": "0.0100",
      "latest_expiration_time": "2026-06-29T14:00:00Z",
      "liquidity_dollars": "0.0000",
      "market_type": "binary",
      "no_ask_dollars": "1.0000",
      "no_bid_dollars": "0.9900",
      "no_sub_title": "78\u00b0 to 79\u00b0",
      "notional_value_dollars": "1.0000",
      "occurrence_datetime": "2026-06-22T14:00:00Z",
      "open_interest_fp": "35220.02",
      "open_time": "2026-06-21T14:00:00Z",
      "previous_price_dollars": "0.0600",
      "previous_yes_ask_dollars": "0.0700",
      "previous_yes_bid_dollars": "0.0600",
      "price_level_structure": "linear_cent",
      "price_ranges": [
        {
          "end": "1.0000",
          "start": "0.0000",
          "step": "0.0100"
        }
      ],
      "response_price_units": "usd_cent",
      "result": "",
      "rules_primary": "If the highest temperature recorded in Central Park, New York for June 22, 2026 as reported by the National Weather Service's Climatological Report (Daily), is between 78-79\u00b0, then the market resolves to Yes.",
      "rules_secondary": "Not all weather data is the same. While checking a source like AccuWeather or Google Weather may help guide your decision, the official and final value used to determine this market is the highest temperature as reported by the corresponding NWS Climatological Report (Daily) linked in the rules above. Preliminary NWS reporting and measurement methods may be subject to underlying rounding and conversion nuances. Traders should exercise caution when interpreting preliminary NWS data.",
      "settlement_timer_seconds": 3600,
      "status": "active",
      "strike_type": "between",
      "subtitle": "78\u00b0 to 79\u00b0",
      "ticker": "KXHIGHNY-26JUN22-B78.5",
      "title": "Will the **high temp in NYC** be 78-79\u00b0 on Jun 22, 2026?",
      "updated_time": "2026-06-21T14:00:00.557958Z",
      "volume_24h_fp": "40657.33",
      "volume_fp": "42242.72",
      "yes_ask_dollars": "0.0100",
      "yes_ask_size_fp": "7263.96",
      "yes_bid_dollars": "0.0000",
      "yes_bid_size_fp": "0.00",
      "yes_sub_title": "78\u00b0 to 79\u00b0"
    },
    {
      "can_close_early": true,
      "cap_strike": 77,
      "close_time": "2026-06-23T04:59:00Z",
      "created_time": "2026-06-21T09:30:41.967743Z",
      "early_close_condition": "The Last Trading Time will be 11:59 PM ET on June 22, 2026 regardless of any data releases or events occurring. Expiration will occur on the sooner of the first 7:00 or 8:00\nAM ET following the release of the data for June 22, 2026, or one week after June 22, 2026.",
      "event_ticker": "KXHIGHNY-26JUN22",
      "expected_expiration_time": "2026-06-23T14:00:00Z",
      "expiration_time": "2026-06-29T14:00:00Z",
      "expiration_value": "",
      "floor_strike": 76,
      "fractional_trading_enabled": true,
      "last_price_dollars": "0.0100",
      "latest_expiration_time": "2026-06-29T14:00:00Z",
      "liquidity_dollars": "0.0000",
      "market_type": "binary",
      "no_ask_dollars": "1.0000",
      "no_bid_dollars": "0.9700",
      "no_sub_title": "76\u00b0 to 77\u00b0",
      "notional_value_dollars": "1.0000",
      "occurrence_datetime": "2026-06-22T14:00:00Z",
      "open_interest_fp": "17636.18",
      "open_time": "2026-06-21T14:00:00Z",
      "previous_price_dollars": "0.3500",
      "previous_yes_ask_dollars": "0.3600",
      "previous_yes_bid_dollars": "0.3500",
      "price_level_structure": "linear_cent",
      "price_ranges": [
        {
          "end": "1.0000",
          "start": "0.0000",
          "step": "0.0100"
        }
      ],
      "response_price_units": "usd_cent",
      "result": "",
      "rules_primary": "If the highest temperature recorded in Central Park, New York for June 22, 2026 as reported by the National Weather Service's Climatological Report (Daily), is between 76-77\u00b0, then the market resolves to Yes.",
      "rules_secondary": "Not all weather data is the same. While checking a source like AccuWeather or Google Weather may help guide your decision, the official and final value used to determine this market is the highest temperature as reported by the corresponding NWS Climatological Report (Daily) linked in the rules above. Preliminary NWS reporting and measurement methods may be subject to underlying rounding and conversion nuances. Traders should exercise caution when interpreting preliminary NWS data.",
      "settlement_timer_seconds": 3600,
      "status": "active",
      "strike_type": "between",
      "subtitle": "76\u00b0 to 77\u00b0",
      "ticker": "KXHIGHNY-26JUN22-B76.5",
      "title": "Will the **high temp in NYC** be 76-77\u00b0 on Jun 22, 2026?",
      "updated_time": "2026-06-21T14:00:00.557958Z",
      "volume_24h_fp": "30337.36",
      "volume_fp": "32000.61",
      "yes_ask_dollars": "0.0300",
      "yes_ask_size_fp": "82.00",
      "yes_bid_dollars": "0.0000",
      "yes_bid_size_fp": "0.00",
      "yes_sub_title": "76\u00b0 to 77\u00b0"
    },
    {
      "can_close_early": true,
      "cap_strike": 75,
      "close_time": "2026-06-23T04:59:00Z",
      "created_time": "2026-06-21T09:30:41.967743Z",
      "early_close_condition": "The Last Trading Time will be 11:59 PM ET on June 22, 2026 regardless of any data releases or events occurring. Expiration will occur on the sooner of the first 7:00 or 8:00\nAM ET following the release of the data for June 22, 2026, or one week after June 22, 2026.",
      "event_ticker": "KXHIGHNY-26JUN22",
      "expected_expiration_time": "2026-06-23T14:00:00Z",
      "expiration_time": "2026-06-29T14:00:00Z",
      "expiration_value": "",
      "floor_strike": 74,
      "fractional_trading_enabled": true,
      "last_price_dollars": "0.0400",
      "latest_expiration_time": "2026-06-29T14:00:00Z",
      "liquidity_dollars": "0.0000",
      "market_type": "binary",
      "no_ask_dollars": "0.9600",
      "no_bid_dollars": "0.9300",
      "no_sub_title": "74\u00b0 to 75\u00b0",
      "notional_value_dollars": "1.0000",
      "occurrence_datetime": "2026-06-22T14:00:00Z",
      "open_interest_fp": "23540.88",
      "open_time": "2026-06-21T14:00:00Z",
      "previous_price_dollars": "0.3700",
      "previous_yes_ask_dollars": "0.3200",
      "previous_yes_bid_dollars": "0.3000",
      "price_level_structure": "linear_cent",
      "price_ranges": [
        {
          "end": "1.0000",
          "start": "0.0000",
          "step": "0.0100"
        }
      ],
      "response_price_units": "usd_cent",
      "result": "",
      "rules_primary": "If the highest temperature recorded in Central Park, New York for June 22, 2026 as reported by the National Weather Service's Climatological Report (Daily), is between 74-75\u00b0, then the market resolves to Yes.",
      "rules_secondary": "Not all weather data is the same. While checking a source like AccuWeather or Google Weather may help guide your decision, the official and final value used to determine this market is the highest temperature as reported by the corresponding NWS Climatological Report (Daily) linked in the rules above. Preliminary NWS reporting and measurement methods may be subject to underlying rounding and conversion nuances. Traders should exercise caution when interpreting preliminary NWS data.",
      "settlement_timer_seconds": 3600,
      "status": "active",
      "strike_type": "between",
      "subtitle": "74\u00b0 to 75\u00b0",
      "ticker": "KXHIGHNY-26JUN22-B74.5",
      "title": "Will the **high temp in NYC** be 74-75\u00b0 on Jun 22, 2026?",
      "updated_time": "2026-06-21T14:00:00.557958Z",
      "volume_24h_fp": "53098.92",
      "volume_fp": "54752.97",
      "yes_ask_dollars": "0.0700",
      "yes_ask_size_fp": "16.00",
      "yes_bid_dollars": "0.0400",
      "yes_bid_size_fp": "271.05",
      "yes_sub_title": "74\u00b0 to 75\u00b0"
    },
    {
      "can_close_early": true,
      "cap_strike": 73,
      "close_time": "2026-06-23T04:59:00Z",
      "created_time": "2026-06-21T09:30:41.967743Z",
      "early_close_condition": "The Last Trading Time will be 11:59 PM ET on June 22, 2026 regardless of any data releases or events occurring. Expiration will occur on the sooner of the first 7:00 or 8:00\nAM ET following the release of the data for June 22, 2026, or one week after June 22, 2026.",
      "event_ticker": "KXHIGHNY-26JUN22",
      "expected_expiration_time": "2026-06-23T14:00:00Z",
      "expiration_time": "2026-06-29T14:00:00Z",
      "expiration_value": "",
      "floor_strike": 72,
      "fractional_trading_enabled": true,
      "last_price_dollars": "0.9600",
      "latest_expiration_time": "2026-06-29T14:00:00Z",
      "liquidity_dollars": "0.0000",
      "market_type": "binary",
      "no_ask_dollars": "0.0800",
      "no_bid_dollars": "0.0500",
      "no_sub_title": "72\u00b0 to 73\u00b0",
      "notional_value_dollars": "1.0000",
      "occurrence_datetime": "2026-06-22T14:00:00Z",
      "open_interest_fp": "31621.48",
      "open_time": "2026-06-21T14:00:00Z",
      "previous_price_dollars": "0.2200",
      "previous_yes_ask_dollars": "0.2200",
      "previous_yes_bid_dollars": "0.2100",
      "price_level_structure": "linear_cent",
      "price_ranges": [
        {
          "end": "1.0000",
          "start": "0.0000",
          "step": "0.0100"
        }
      ],
      "response_price_units": "usd_cent",
      "result": "",
      "rules_primary": "If the highest temperature recorded in Central Park, New York for June 22, 2026 as reported by the National Weather Service's Climatological Report (Daily), is between 72-73\u00b0, then the market resolves to Yes.",
      "rules_secondary": "Not all weather data is the same. While checking a source like AccuWeather or Google Weather may help guide your decision, the official and final value used to determine this market is the highest temperature as reported by the corresponding NWS Climatological Report (Daily) linked in the rules above. Preliminary NWS reporting and measurement methods may be subject to underlying rounding and conversion nuances. Traders should exercise caution when interpreting preliminary NWS data.",
      "settlement_timer_seconds": 3600,
      "status": "active",
      "strike_type": "between",
      "subtitle": "72\u00b0 to 73\u00b0",
      "ticker": "KXHIGHNY-26JUN22-B72.5",
      "title": "Will the **high temp in NYC** be 72-73\u00b0 on Jun 22, 2026?",
      "updated_time": "2026-06-21T14:00:00.557958Z",
      "volume_24h_fp": "66097.63",
      "volume_fp": "68383.94",
      "yes_ask_dollars": "0.9500",
      "yes_ask_size_fp": "206.00",
      "yes_bid_dollars": "0.9200",
      "yes_bid_size_fp": "12.00",
      "yes_sub_title": "72\u00b0 to 73\u00b0"
    }
  ],
  "cursor": null
}